{
  "hash": "fc588fd3",
  "browserHash": "3a406b01",
  "optimized": {
    "react": {
      "src": "../../node_modules/react/index.js",
      "file": "react.js",
      "fileHash": "dabf5ec9",
      "needsInterop": true
    },
    "react-dom/client": {
      "src": "../../node_modules/react-dom/client.js",
      "file": "react-dom_client.js",
      "fileHash": "a3c8a243",
      "needsInterop": true
    },
    "react-redux": {
      "src": "../../node_modules/react-redux/es/index.js",
      "file": "react-redux.js",
      "fileHash": "bef81b5f",
      "needsInterop": false
    },
    "axios": {
      "src": "../../node_modules/axios/index.js",
      "file": "axios.js",
      "fileHash": "082072d1",
      "needsInterop": false
    },
    "react-router-dom": {
      "src": "../../node_modules/react-router-dom/dist/index.js",
      "file": "react-router-dom.js",
      "fileHash": "8f508980",
      "needsInterop": false
    },
    "@reduxjs/toolkit": {
      "src": "../../node_modules/@reduxjs/toolkit/dist/redux-toolkit.esm.js",
      "file": "@reduxjs_toolkit.js",
      "fileHash": "38962ee6",
      "needsInterop": false
    },
    "react-icons/bs": {
      "src": "../../node_modules/react-icons/bs/index.esm.js",
      "file": "react-icons_bs.js",
      "fileHash": "c5216ee2",
      "needsInterop": false
    },
    "react-icons/ai": {
      "src": "../../node_modules/react-icons/ai/index.esm.js",
      "file": "react-icons_ai.js",
      "fileHash": "a8c79712",
      "needsInterop": false
    }
  },
  "chunks": {
    "chunk-DZXRV6RW": {
      "file": "chunk-DZXRV6RW.js"
    },
    "chunk-6NBOS2UH": {
      "file": "chunk-6NBOS2UH.js"
    },
    "chunk-ZAUFE7H7": {
      "file": "chunk-ZAUFE7H7.js"
    },
    "chunk-UXIASGQL": {
      "file": "chunk-UXIASGQL.js"
    }
  }
}